{
  "schema_version": "1.0",
  "gate": "MOTION-04",
  "model_calls": 0,
  "golden_count": 6,
  "passed": true,
  "check_count": 42,
  "goldens": [
    {
      "golden_id": "buoyancy",
      "passed": true,
      "check_count": 7,
      "model_function": "buoyancyState",
      "source_sha256": "c48380438c8eccad3d4d239bc5fac41c3e8235c04db049d549fe41a7ceeb7c1d",
      "failures": []
    },
    {
      "golden_id": "day_night",
      "passed": true,
      "check_count": 7,
      "model_function": "dayNightState",
      "source_sha256": "c1ab08047ca0ec56fdb3614817385d3e49499f2abc93e04fc4c64abb0e7f5d87",
      "failures": []
    },
    {
      "golden_id": "moon_phases",
      "passed": true,
      "check_count": 7,
      "model_function": "moonState",
      "source_sha256": "6200e0031d6ebd6e7e310a6ad05c9200eb7aa6f067a0867244920d0cf86a8e20",
      "failures": []
    },
    {
      "golden_id": "pendulum",
      "passed": true,
      "check_count": 7,
      "model_function": "pendulumState",
      "source_sha256": "1ba75dabf4f1a4bf26616cb9d9424f7e6222ca17663b422efa5f0ba1e84fe45d",
      "failures": []
    },
    {
      "golden_id": "simple_circuit",
      "passed": true,
      "check_count": 7,
      "model_function": "circuitState",
      "source_sha256": "02e65cd62b52422094bfdec705aedf432fec92daa1ab40624bb9680639d44914",
      "failures": []
    },
    {
      "golden_id": "sound_pitch",
      "passed": true,
      "check_count": 7,
      "model_function": "soundState",
      "source_sha256": "e9ba8574b306d15502b886671d3fafe04b218ccea5de715dbea584e4e81727dd",
      "failures": []
    }
  ]
}
